{"is_source_file": true, "file_id": 15, "git_revision": "", "state": 1, "description": "", "external_files": [], "external_methods": [], "published": [], "classes": [], "methods": [], "calls": [], "search-terms": [], "ctags": [{"_type": "tag", "name": "Footer", "path": "/home/kavia/workspace/code-generation/react-tailwind-web-interface-2092-2101/frontend_app/src/components/Footer.jsx", "pattern": "/^export default function Footer() {$/", "language": "JavaScript", "kind": "function", "signature": "()"}], "format": "JavaScript", "hash": "ef4996bf900018edff18cba579686cde", "format-version": 4, "code-base-name": "frontend_app", "filename": "frontend_app/src/components/Footer.jsx", "knowledge_revision": 31}